manageritm_client/__init__.py
manageritm_client/manageritm_client.py
manageritm_client/manageritm_command_client.py
manageritm_client/manageritm_proxy_client.py
manageritm_client-0.1.0.dist-info/LICENSE
manageritm_client-0.1.0.dist-info/METADATA
manageritm_client-0.1.0.dist-info/WHEEL
manageritm_client-0.1.0.dist-info/RECORD
